UniDeskCppExt/__init__.pyi
UniDeskCppExt/udcpptools.cp310-win_amd64.pyd
UniDeskCppExt/udcpptools.pyi
unideskcppext-0.0.1b2025082002.dist-info/licenses/LICENSE
unideskcppext-0.0.1b2025082002.dist-info/METADATA
unideskcppext-0.0.1b2025082002.dist-info/WHEEL
unideskcppext-0.0.1b2025082002.dist-info/top_level.txt
unideskcppext-0.0.1b2025082002.dist-info/RECORD
