Metadata-Version: 2.4
Name: UniDeskCppExt
Version: 0.0.1b2025082002
Summary: The C++ Extension for Uniquenium
Author: Admibrill
Author-email: admibrill@outlook.com
Requires-Python: >=3.7
License-File: LICENSE
Provides-Extra: test
Requires-Dist: pytest>=6.0; extra == "test"
Dynamic: author
Dynamic: author-email
Dynamic: description
Dynamic: description-content-type
Dynamic: license-file
Dynamic: provides-extra
Dynamic: requires-python
Dynamic: summary
